pivoteer/__init__.py
pivoteer/core.py
pivoteer/exceptions.py
pivoteer/models.py
pivoteer/pivot_cache_updater.py
pivoteer/table_resizer.py
pivoteer/template_engine.py
pivoteer/utils.py
pivoteer/xml_engine.py
pivoteer-0.2.0.dist-info/METADATA
pivoteer-0.2.0.dist-info/WHEEL
pivoteer-0.2.0.dist-info/licenses/LICENSE
pivoteer-0.2.0.dist-info/RECORD
