Metadata-Version: 2.4
Name: pivoteer
Version: 0.2.0
Summary: Inject pandas DataFrames into Excel templates with table resizing and pivot refresh.
Project-URL: Repository, https://github.com/flitzrrr/pivoteer
Project-URL: Issues, https://github.com/flitzrrr/pivoteer/issues
Author: Martin
Maintainer: Martin
License: MIT
License-File: LICENSE
Classifier: Development Status :: 3 - Alpha
Classifier: Intended Audience :: Developers
Classifier: License :: OSI Approved :: MIT License
Classifier: Operating System :: OS Independent
Classifier: Programming Language :: Python :: 3
Classifier: Programming Language :: Python :: 3.10
Classifier: Programming Language :: Python :: 3.11
Classifier: Programming Language :: Python :: 3.12
Classifier: Topic :: Office/Business
Classifier: Topic :: Software Development :: Libraries
Requires-Python: >=3.10
Requires-Dist: lxml>=5.2.0
Requires-Dist: pandas>=2.2.0
Provides-Extra: dev
Requires-Dist: pytest>=8.3.0; extra == 'dev'
Requires-Dist: xlsxwriter>=3.2.0; extra == 'dev'
